> This article is converted from Wikipedia: [루아 \(프로그래밍 언어\)](https://ko.wikipedia.org/wiki/루아_\(프로그래밍_언어\)).


**루아**(Lua) 프로그래밍 언어는 가벼운 [명령형](../Page/명령형_프로그래밍.md "wikilink")/[절차적](../Page/절차적_프로그래밍.md "wikilink") 언어로, [확장 언어로](https://ko.wikipedia.org/wiki/확장_언어 "wikilink") 쓰일 수 있는 [스크립팅 언어를](https://ko.wikipedia.org/wiki/스크립팅_언어 "wikilink") 주 목적으로 설계되었다. 그러나 알고리즘적 설계(테이블 등)가 많이 내재되어 있고 인터프리터(언어 실행기)로만 코드뭉치를 실행할 수 있으므로, [선언형 언어로도](../Page/선언형_프로그래밍_언어.md "wikilink") 볼 수 있다. 루아는 "달"을 의미하는 [포르투갈어](../Page/포르투갈어.md "wikilink") 단어이다.

## 역사

루아는 1993년에 [브라질](../Page/브라질.md "wikilink")의 [리우 데자네이로에](https://ko.wikipedia.org/wiki/리우_데자네이로 "wikilink") 있는 [교황청 대학교의](https://ko.wikipedia.org/wiki/교황청_대학교 "wikilink") 컴퓨터 그래픽 기술 그룹 회원인 [루이스 엔리케 데피게이레두](https://ko.wikipedia.org/wiki/루이스_엔리케_데피게이레두 "wikilink")(Luiz Henrique de Figueiredo), [호베르투 이에루잘림스시와](../Page/호베르투_이에루잘림스시.md "wikilink") [발데마르 셀레스](https://ko.wikipedia.org/wiki/발데마르_셀레스 "wikilink")(Waldemar Celes)가 만들었다. 5.0 버전 이전의 루아는 [BSD 라이선스와](https://ko.wikipedia.org/wiki/BSD_라이선스 "wikilink") 비슷한 라이선스에 따라 공개되었고, 5.0부터는 [MIT 라이선스에](https://ko.wikipedia.org/wiki/MIT_라이선스 "wikilink") 따라 공개되고 있어서, 개인적으로나 상업적으로나 허락없이 사용하는 것이 가능하며, [GNU](../Page/GNU.md "wikilink")같은 저작권 표시가 요구되지 않는다. 다만, 사용 중 발생하는 문제에 관해서는 루아의 개발자 측에서는 책임을 지지 않으며\[1\], 루아를 사용함에 있어서 제품이나 문서 같은 곳에 루아 마크나 홈페이지로의 링크를 넣는 등 감사를 남겨줄 것을 권하고 있다.

## 기능

루아는 [확장 언어와](https://ko.wikipedia.org/wiki/확장_언어 "wikilink") [스크립트 언어를](../Page/스크립트_언어.md "wikilink") 지향하고 있으며, 충분히 작기 때문에 많은 플랫폼에서 사용할 수 있다. 루아는 [불 값](https://ko.wikipedia.org/wiki/불_값 "wikilink"), [숫자](../Page/숫자.md "wikilink")(기본적으로 배정밀도 [실수형](https://ko.wikipedia.org/wiki/실수형 "wikilink")), 그리고 [문자열](https://ko.wikipedia.org/wiki/문자열 "wikilink")과 같은 적은 수의 기본 데이터형만을 지원하며, [배열](../Page/배열.md "wikilink"), [집합](https://ko.wikipedia.org/wiki/집합_\(전산학\) "wikilink"), [해시 테이블](../Page/해시_테이블.md "wikilink"), [리스트](../Page/리스트_\(컴퓨팅\).md "wikilink"), [레코드와](../Page/레코드_\(컴퓨터_과학\).md "wikilink") 같은 전형적인 데이터 구조는 모두 [연관 배열과](https://ko.wikipedia.org/wiki/연관_배열 "wikilink") 유사한 루아의 테이블 자료형으로 구현하고 있다. 이름 공간과 객체들 역시 이 테이블을 사용하여 표현할 수 있다. 최소한의 자료형을 사용함으로써 루아는 성능과 크기 사이의 균형을 맞추려는 시도를 하였다.

루아에서 연산식들의 의미는 메타테이블에 있는 내장 함수들을 재지정해서 확장하거나 변경할 수 있다. 또한 루아는 [고차원 함수나](https://ko.wikipedia.org/wiki/고차원_함수 "wikilink") [가비지 콜렉션과](https://ko.wikipedia.org/wiki/가비지_콜렉션 "wikilink") 같은 고급 기능을 지원하고 있다. 이러한 많은 기능들을 사용하면 루아에서 [객체 지향적인](../Page/객체_지향_프로그래밍.md "wikilink") 프로그램을 만들 수 있다.

### 예제 코드

다음은 ["Hello, world\!"를](https://ko.wikipedia.org/wiki/Hello_world_프로그램 "wikilink") 출력하는 전형적인 프로그램이다:

``` lua
 print "Hello, world!"
```

다음은 [계승](../Page/계승.md "wikilink")을 계산하는 프로그램으로, [재귀 호출](https://ko.wikipedia.org/wiki/재귀_호출 "wikilink") 함수의 예시를 보이고 있다.

``` lua
 function factorial(n)
     if n == 0 then
         return 1
     end

     return n * factorial(n - 1)
 end
```

## 내부구조

루아 프로그램은 직접적으로 [인터프리트되지](https://ko.wikipedia.org/wiki/인터프리트_언어 "wikilink") 않고, [바이트 코드로](https://ko.wikipedia.org/wiki/바이트_코드 "wikilink") [컴파일](https://ko.wikipedia.org/wiki/컴파일 "wikilink")되어 루아 [가상 머신에서](../Page/가상_머신.md "wikilink") 실행 된다. 컴파일 과정은 [실행 시간에](https://ko.wikipedia.org/wiki/실행_시간_\(컴퓨터_프로그래밍\) "wikilink") 사용자가 느끼지 못하게 시행되지만, 로딩되는 시간을 줄여서 성능을 향상시키거나 컴파일러가 없는 메모리 사용량에 제약이 있는 환경에서 실행하기 위해서 미리 컴파일할 수도 있다.

루아 가상머신은 다른 대부분의 가상머신이 스택 기반인 것과는 달리 CPU의 구조와 닮은 레지스터 기반이라서 실제 하드웨어 디자인과 유사성이 있다. 레지스터 기반의 가상머신은 값들을 과다하게 복사하는 것을 방지할 수 있고, 함수를 구성하는 명령어를 줄일 수 있는 것이 장점이다. Lua 5의 가상머신은 최초의 널리 사용되는 레지스터 기반의 가상머신 중 하나이며, 다른 두 개의 잘 알려진 레지스터 기반의 가상머신이 펄의 패롯과 안드로이드의 달빅이다.

다음은 위에 있는 계승을 계산하는 프로그램의 바이트 코드이다: (루아 5.0 기준)

`function <factorial.lua:1> (10 instructions, 40 bytes at 00326DA0)`
`1 param, 3 stacks, 0 upvalues, 1 local, 3 constants, 0 functions`
`    1   [2] EQ          0 0 250 ; compare value to 0`
`    2   [2] JMP         0 2     ; to line 5`
`    3   [3] LOADK       1 1     ; 1`
`    4   [3] RETURN      1 2 0`
`    5   [6] GETGLOBAL   1 2     ; fact`
`    6   [6] SUB         2 0 251 ; - 1`
`    7   [6] CALL        1 2 2`
`    8   [6] MUL         1 0 1`
`    9   [6] RETURN      1 2 0`
`    10  [7] RETURN      0 1 0`

## 응용 프로그램

루아는 특히 게임에서 많이 사용된다. 예를 들어서 [루커스아츠](https://ko.wikipedia.org/wiki/루커스아츠 "wikilink")의 [원숭이 섬으로부터의 탈출](https://ko.wikipedia.org/wiki/원숭이_섬으로부터의_탈출 "wikilink") [어드벤처 게임과](../Page/어드벤처_게임.md "wikilink") 같은 많은 상업적 응용 프로그램과, [앵그리 버드와](https://ko.wikipedia.org/wiki/앵그리_버드 "wikilink") 그 변형들과 같은 비상업적 응용 프로그램들이 루아를 사용하고 있다. 또, [MMORPG](https://ko.wikipedia.org/wiki/MMORPG "wikilink")인 [월드 오브 워크래프트에서는](../Page/월드_오브_워크래프트.md "wikilink") 사용자 인터페이스, 캐릭터 애니메이션, 그리고 게임 상의 세계의 외관을 루아를 사용해서 변경할 수 있다. 또한 [바이오웨어](../Page/바이오웨어.md "wikilink")의 [PC](../Page/개인용_컴퓨터.md "wikilink") 롤플레잉 게임인 [네버윈터 나이츠에서는](../Page/네버윈터_나이츠.md "wikilink") 루아를 모듈 스크립팅 언어로 사용하고 있으며, [ToME](https://ko.wikipedia.org/wiki/ToME "wikilink")나 [H-World](https://ko.wikipedia.org/wiki/H-World "wikilink")와 같은 오픈 소스 게임에서도 사용된다. 멀티플레이 게임인 [There](https://ko.wikipedia.org/wiki/There "wikilink")에서는 자동차들과 애니메이션을 조정하기 위해서 [Therescript](https://ko.wikipedia.org/wiki/Therescript "wikilink")라는 루아의 변형된 버전을 사용하고 있다. 시드 마이어의 문명 V와 문명: 비욘드 어스에서도 XML과 함께 루아가 이용되고 있다. 더 바인딩 오브 아이작: 리버스 이후의 확장판인 애프터버스+에서는 루아를 통해 게임 내부 소스를 고칠 수 있게 된다고 한다. 또한, 미국의 온라인 게임 플랫폼 'Roblox' 에서도 루아를 이용해 게임을 만들고 있다.

[X 윈도 매니저인](https://ko.wikipedia.org/wiki/X_윈도_매니저 "wikilink") [Ion은](https://ko.wikipedia.org/wiki/Ion_\(X_윈도_매니저\) "wikilink") 사용자에 맞게 인터페이스를 조정하거나 확장하는 데 루아를 사용하고 있다.

[TeX](../Page/TeX.md "wikilink")에서도 루아 언어를 [TeX](../Page/TeX.md "wikilink") 소스 코드 안에서 사용할 수 있는 [LuaTeX](https://ko.wikipedia.org/wiki/LuaTeX "wikilink")이 나와 있다.

또한, 이 Lua언어를 기반으로 한 CoronaSDK라는 소프트웨어가 있는데, 이를 사용하면 IOS와 Android (게임)개발을 쉽고 빠르게 할 수 있다. 요즘에는 Cocos-2d에서도 lua언어를 지원한다고 한다.

## 각주

  - 내용주

## 외부 링크

  -
  - [루아 사용자 위키](http://lua-users.org/wiki/LuaAddons), [유즈모드 위키를](https://ko.wikipedia.org/wiki/유즈모드_위키 "wikilink") 사용함.

  - [LuaBind](http://luabind.sf.net) C++의 함수와 클래스들을 루아에서 사용할 수 있게 하는 라이브러리.

  - [tolua](http://www.tecgraf.puc-rio.br/~celes/tolua/) 별도의 템플릿을 만들어 바인드코드를 생성해주는 솔루션.

  - [CPB](https://web.archive.org/web/20050404004755/http://www.thomasandamy.com/projects/CPB/) C++ 함수와 변수들을 루아에서 접근하기 위한 강력한 솔루션.

  - [루아를 웹 페이지 그래픽 애플릿으로 사용하기](http://www.yindo.com/)

  - [luaforge](https://web.archive.org/web/20070202005230/http://luaforge.net/) 루아관련 오픈소스 프로젝트 모음. sourceforge 엔진기반사이트.

  - [redwiki.net:Lua](https://web.archive.org/web/20050426183809/http://www.redwiki.net/wiki/wiki.php/Lua) redwiki.net의 lua관련 페이지

[분류:스크립트 언어](https://ko.wikipedia.org/wiki/분류:스크립트_언어 "wikilink") [분류:브라질의 발명품](https://ko.wikipedia.org/wiki/분류:브라질의_발명품 "wikilink") [분류:크로스 플랫폼 소프트웨어](https://ko.wikipedia.org/wiki/분류:크로스_플랫폼_소프트웨어 "wikilink") [분류:객체 지향 프로그래밍 언어](https://ko.wikipedia.org/wiki/분류:객체_지향_프로그래밍_언어 "wikilink") [분류:프로토타입 기반 프로그래밍 언어](https://ko.wikipedia.org/wiki/분류:프로토타입_기반_프로그래밍_언어 "wikilink") [분류:1993년 개발된 프로그래밍 언어](https://ko.wikipedia.org/wiki/분류:1993년_개발된_프로그래밍_언어 "wikilink") [분류:C로 작성된 자유 소프트웨어](https://ko.wikipedia.org/wiki/분류:C로_작성된_자유_소프트웨어 "wikilink") [분류:MIT 라이선스 소프트웨어](https://ko.wikipedia.org/wiki/분류:MIT_라이선스_소프트웨어 "wikilink") [분류:크로스 플랫폼 자유 소프트웨어](https://ko.wikipedia.org/wiki/분류:크로스_플랫폼_자유_소프트웨어 "wikilink") [분류:동적 프로그래밍 언어](https://ko.wikipedia.org/wiki/분류:동적_프로그래밍_언어 "wikilink") [분류:자유 라이브러리](https://ko.wikipedia.org/wiki/분류:자유_라이브러리 "wikilink") [분류:자유 컴파일러와 인터프리터](https://ko.wikipedia.org/wiki/분류:자유_컴파일러와_인터프리터 "wikilink")

1.